PyZkUI/__init__.py
PyZkUI/config.py
PyZkUI/models.py
PyZkUI/utils.py
PyZkUI/views.py
PyZkUI/static/bootstrap-4.5.3.bundle.min.js
PyZkUI/static/bootstrap-4.5.3.min.css
PyZkUI/static/favicon.ico
PyZkUI/static/font-awesome-4.7.0.min.css
PyZkUI/static/home.js
PyZkUI/static/jquery-3.5.1.min.js
PyZkUI/static/tree.js
PyZkUI/templates/_modal_0.html
PyZkUI/templates/_modal_1.html
PyZkUI/templates/_modal_2.html
PyZkUI/templates/_nav_0.html
PyZkUI/templates/_nav_1.html
PyZkUI/templates/home.html
PyZkUI/templates/tree.html
PyZkUI-1.2.2.dist-info/LICENSE
PyZkUI-1.2.2.dist-info/METADATA
PyZkUI-1.2.2.dist-info/WHEEL
PyZkUI-1.2.2.dist-info/entry_points.txt
PyZkUI-1.2.2.dist-info/top_level.txt
PyZkUI-1.2.2.dist-info/RECORD
