Metadata-Version: 2.1
Name: PyZkUI
Version: 1.2.2
Summary: A Python Zookeeper UI.
Home-page: https://github.com/Harpsichord1207/PyZkUI
Author: Harpsichord
Author-email: tliu1217@163.com
License: MPL 2.0
Keywords: Flask Zookeeper UI
Platform: any
Classifier: Programming Language :: Python :: 3.8
Classifier: Environment :: Web Environment
Classifier: Framework :: Flask
Requires-Dist: flask
Requires-Dist: waitress
Requires-Dist: kazoo
Requires-Dist: Flask-SQLAlchemy
